wiz_trader/__init__.py
wiz_trader/apis/__init__.py
wiz_trader/apis/client.py
wiz_trader/quotes/__init__.py
wiz_trader/quotes/client.py
wiz_trader-0.41.0.dist-info/METADATA
wiz_trader-0.41.0.dist-info/WHEEL
wiz_trader-0.41.0.dist-info/top_level.txt
wiz_trader-0.41.0.dist-info/RECORD
