Metadata-Version: 2.4
Name: wiz_trader
Version: 0.41.0
Summary: A Python SDK for connecting to the Wizzer.
Home-page: https://bitbucket.org/wizzer-tech/quotes_sdk.git
Author: Pawan Wagh
Author-email: Pawan Wagh <pawan@wizzer.in>
License: MIT
Project-URL: Homepage, https://bitbucket.org/wizzer-tech/quotes_sdk.git
Project-URL: Bug Tracker, https://bitbucket.org/wizzer-tech/quotes_sdk/issues
Keywords: finance,trading,sdk
Classifier: Development Status :: 3 - Alpha
Classifier: Intended Audience :: Financial and Insurance Industry
Classifier: Intended Audience :: Developers
Classifier: Programming Language :: Python :: 3
Classifier: Operating System :: OS Independent
Classifier: License :: OSI Approved :: MIT License
Classifier: Topic :: Office/Business :: Financial
Classifier: Topic :: Software Development :: Libraries :: Python Modules
Requires-Python: >=3.6
Requires-Dist: websockets
Requires-Dist: requests
Dynamic: author
Dynamic: home-page
Dynamic: requires-python
